{
    "identifier": "new",
    "data": [
        "https://sdk.bitmoji.com/render/panel/20053959-12430618-b508-4d2e-b2c8-17eaf61217b2-v1.webp?transparent=1&scale=0",
        "https://sdk.bitmoji.com/render/panel/20053961-12430618-b508-4d2e-b2c8-17eaf61217b2-v1.webp?transparent=1&scale=0",
        "https://sdk.bitmoji.com/render/panel/20053717-12430618-b508-4d2e-b2c8-17eaf61217b2-v1.webp?transparent=1&scale=0",
        "https://sdk.bitmoji.com/render/panel/20053718-12430618-b508-4d2e-b2c8-17eaf61217b2-v1.webp?transparent=1&scale=0",
        "https://sdk.bitmoji.com/render/panel/20053723-12430618-b508-4d2e-b2c8-17eaf61217b2-v1.webp?transparent=1&scale=0",
        "https://sdk.bitmoji.com/render/panel/20053181-12430618-b508-4d2e-b2c8-17eaf61217b2-v1.webp?transparent=1&scale=0",
        "https://sdk.bitmoji.com/render/panel/20053185-12430618-b508-4d2e-b2c8-17eaf61217b2-v1.webp?transparent=1&scale=0",
        "https://sdk.bitmoji.com/render/panel/20053157-12430618-b508-4d2e-b2c8-17eaf61217b2-v1.webp?transparent=1&scale=0",
        "https://sdk.bitmoji.com/render/panel/20052973-12430618-b508-4d2e-b2c8-17eaf61217b2-v1.webp?transparent=1&scale=0",
        "https://sdk.bitmoji.com/render/panel/20053155-12430618-b508-4d2e-b2c8-17eaf61217b2-v1.webp?transparent=1&scale=0",
        "https://sdk.bitmoji.com/render/panel/20053154-12430618-b508-4d2e-b2c8-17eaf61217b2-v1.webp?transparent=1&scale=0",
        "https://sdk.bitmoji.com/render/panel/20053000-12430618-b508-4d2e-b2c8-17eaf61217b2-v1.webp?transparent=1&scale=0",
        "https://sdk.bitmoji.com/render/panel/20053424-12430618-b508-4d2e-b2c8-17eaf61217b2-v1.webp?transparent=1&scale=0",
        "https://sdk.bitmoji.com/render/panel/20053423-12430618-b508-4d2e-b2c8-17eaf61217b2-v1.webp?transparent=1&scale=0",
        "https://sdk.bitmoji.com/render/panel/20053426-12430618-b508-4d2e-b2c8-17eaf61217b2-v1.webp?transparent=1&scale=0",
        "https://sdk.bitmoji.com/render/panel/20053174-12430618-b508-4d2e-b2c8-17eaf61217b2-v1.webp?transparent=1&scale=0",
        "https://sdk.bitmoji.com/render/panel/20053175-12430618-b508-4d2e-b2c8-17eaf61217b2-v1.webp?transparent=1&scale=0",
        "https://sdk.bitmoji.com/render/panel/20053176-12430618-b508-4d2e-b2c8-17eaf61217b2-v1.webp?transparent=1&scale=0"
    ],
    "config": {
        "identifier": "new",
        "name": "Bitmoji new",
        "publisher": "Bitmoji",
        "tray_image_file": "tray-icon.png",
        "image_data_version": "1",
        "avoid_cache": false,
        "publisher_email": "",
        "publisher_website": "",
        "privacy_policy_website": "",
        "license_agreement_website": "",
        "stickers": [
            {
                "image_file": "new_0.webp",
                "emojis": [
                    "☕"
                ]
            },
            {
                "image_file": "new_1.webp",
                "emojis": [
                    "☕"
                ]
            },
            {
                "image_file": "new_2.webp",
                "emojis": [
                    "☕"
                ]
            },
            {
                "image_file": "new_3.webp",
                "emojis": [
                    "☕"
                ]
            },
            {
                "image_file": "new_4.webp",
                "emojis": [
                    "☕"
                ]
            },
            {
                "image_file": "new_5.webp",
                "emojis": [
                    "☕"
                ]
            },
            {
                "image_file": "new_6.webp",
                "emojis": [
                    "☕"
                ]
            },
            {
                "image_file": "new_7.webp",
                "emojis": [
                    "☕"
                ]
            },
            {
                "image_file": "new_8.webp",
                "emojis": [
                    "☕"
                ]
            }
        ]
    }
}